README.md
setup.py
dir2html/__init__.py
dir2html/__main__.py
dir2html/copy_files.py
dir2html/get_assets.py
dir2html/get_images.py
dir2html/render_template.py
dir2html.egg-info/PKG-INFO
dir2html.egg-info/SOURCES.txt
dir2html.egg-info/dependency_links.txt
dir2html.egg-info/entry_points.txt
dir2html.egg-info/top_level.txt
dir2html/resources/album-template.html
dir2html/resources/image-template.html
dir2html/resources/test.html
dir2html/resources/assets/album.css
dir2html/resources/assets/bootstrap.min.css
dir2html/resources/assets/bootstrap.min.js
dir2html/resources/assets/holder.min.js
dir2html/resources/assets/jquery-slim.min.js
dir2html/resources/assets/popper.min.js